django_jinja_markdown/__init__.py
django_jinja_markdown/extensions.py
django_jinja_markdown/templatetags/__init__.py
django_jinja_markdown/templatetags/md.py
django_jinja_markdown-1.2.data/data/CHANGELOG
django_jinja_markdown-1.2.data/data/LICENSE
django_jinja_markdown-1.2.data/data/README.rst
django_jinja_markdown-1.2.data/data/tox.ini
django_jinja_markdown-1.2.dist-info/licenses/LICENSE
django_jinja_markdown-1.2.dist-info/METADATA
django_jinja_markdown-1.2.dist-info/WHEEL
django_jinja_markdown-1.2.dist-info/top_level.txt
django_jinja_markdown-1.2.dist-info/RECORD
