Metadata-Version: 2.4
Name: django-jinja-markdown
Version: 1.2
Summary: Django-Jinja (Jinja2) extension and filter for parsing markdown text markup.
Author-email: Paul McLanahan <paul@mclanahan.net>
License-Expression: MIT
Project-URL: Changelog, https://github.com/mozmeao/django-jinja-markdown/blob/master/CHANGELOG
Project-URL: Homepage, https://github.com/mozmeao/django-jinja-markdown
Project-URL: Issues, https://github.com/mozmeao/django-jinja-markdown/issues
Classifier: Development Status :: 5 - Production/Stable
Classifier: Environment :: Web Environment
Classifier: Framework :: Django
Classifier: Intended Audience :: Developers
Classifier: Operating System :: OS Independent
Classifier: Programming Language :: Python
Classifier: Programming Language :: Python :: 3 :: Only
Classifier: Programming Language :: Python :: 3.9
Classifier: Programming Language :: Python :: 3.10
Classifier: Programming Language :: Python :: 3.11
Classifier: Programming Language :: Python :: 3.12
Classifier: Programming Language :: Python :: 3.13
Classifier: Topic :: Software Development :: Code Generators
Classifier: Topic :: Text Processing :: Markup
Requires-Python: >=3.9
License-File: LICENSE
Requires-Dist: django-jinja>=2.11
Requires-Dist: jinja2>=3.1.6
Requires-Dist: markdown>=3.5
Requires-Dist: markupsafe>=3
Provides-Extra: dev
Requires-Dist: ruff; extra == "dev"
Dynamic: license-file
